weightedDelaunay/__init__.py
weightedDelaunay-1.0.5.dist-info/LICENSE.md
weightedDelaunay-1.0.5.dist-info/METADATA
weightedDelaunay-1.0.5.dist-info/WHEEL
weightedDelaunay-1.0.5.dist-info/top_level.txt
weightedDelaunay-1.0.5.dist-info/RECORD
