Metadata-Version: 2.1
Name: weightedDelaunay
Version: 1.0.5
Summary: A packaged used to calculate the weighted delaunay triangulation in N-dimensions
Home-page: https://github.com/Ale0x78/weightedDelaunay
Author: Mark Klose, Bansi Chhatrala, Alex Nahapetyan
Author-email: mwklose@ncsu.edu, bschhatr@ncsu.edu, anahape@ncsu.edu
License: UNKNOWN
Project-URL: Bug Tracker, https://github.com/Ale0x78/weightedDelaunay/issues
Platform: UNKNOWN
Classifier: Programming Language :: Python :: 3
Classifier: License :: OSI Approved :: MIT License
Classifier: Operating System :: OS Independent
Requires-Python: >=3.6
Requires-Dist: scipy
Requires-Dist: numpy
